todo_app/__init__.py
todo_app/db.py
todo_app/display.py
todo_app/todo.py
python_todo-0.4.dist-info/LICENSE
python_todo-0.4.dist-info/METADATA
python_todo-0.4.dist-info/WHEEL
python_todo-0.4.dist-info/entry_points.txt
python_todo-0.4.dist-info/top_level.txt
python_todo-0.4.dist-info/RECORD
