Metadata-Version: 2.1
Name: python-todo
Version: 0.4
Summary: A command line todo application
Home-page: http://github.com/weaverdyl/python-todo
Author: Dylan Weaver
Author-email: dylan@weaverdyl.com
License: MIT
Platform: UNKNOWN
Requires-Dist: terminaltables
